 [
            {
                "gender": "Male",
                "name": {
                    "title": "mr",
                    "first": "ed",
                    "last": "duncan"
                },
                "location": {
                    "street": "3939 george street",
                    "city": "york",
                    "state": "northumberland",
                    "postcode": "D7R 0NP",
                    "coordinates": {
                        "latitude": "10.6134",
                        "longitude": "-19.9905"
                    },
                    "timezone": {
                        "offset": "-6:00",
                        "description": "Central Time (US & Canada), Mexico City"
                    }
                },
                "email": "ed.duncan@example.com",
                "login": {
                    "uuid": "43362fa0-2510-4627-8663-922c9332fcdc",
                    "username": "happydog649",
                    "password": "helper",
                    "salt": "kwecyjEW",
                    "md5": "571fe061bc1a3de005a3f8b0fd28fb4d",
                    "sha1": "353f59a0370ee039ed77dad57e27e8c6e400a8cd",
                    "sha256": "c47f81a7a819e5b28d599beafcbe086cf4d0588f357ed815ac83506c159aae9a"
                },
                "dob": {
                    "date": "1952-12-16T16:45:50Z",
                    "age": 66
                },
                "registered": {
                    "date": "2004-06-08T23:35:26Z",
                    "age": 14
                },
                "phone": "017684 55532",
                "cell": "0723-313-816",
                "id": {
                    "name": "NINO",
                    "value": "SP 90 46 60 V"
                },
                "picture": {
                    "large": "https://randomuser.me/api/portraits/men/75.jpg",
                    "medium": "https://randomuser.me/api/portraits/med/men/75.jpg",
                    "thumbnail": "https://randomuser.me/api/portraits/thumb/men/75.jpg"
                },
                "nat": "GB"
            },
            {
                "gender": "male",
                "name": {
                    "title": "mr",
                    "first": "albert",
                    "last": "frings"
                },
                "location": {
                    "street": "wiesenweg 7",
                    "city": "sulzbach/saar",
                    "state": "saarland",
                    "postcode": 73278,
                    "coordinates": {
                        "latitude": "-49.2182",
                        "longitude": "-89.8691"
                    },
                    "timezone": {
                        "offset": "+4:00",
                        "description": "Abu Dhabi, Muscat, Baku, Tbilisi"
                    }
                },
                "email": "albert.frings@example.com",
                "login": {
                    "uuid": "6cf50a51-5f3c-4125-a259-2114c2b69ce6",
                    "username": "organicmeercat854",
                    "password": "shadows",
                    "salt": "HHI2qRv0",
                    "md5": "1281f1b963c13a42aa25ffc112577f99",
                    "sha1": "a036495cbe65fd5d04ad798b6a1cb1ffedb91edb",
                    "sha256": "85438120fa2231ef49899c10b6c0a1a58ac82bc77e5d66f8b3d7c786c29b5af6"
                },
                "dob": {
                    "date": "1980-11-22T05:33:40Z",
                    "age": 38
                },
                "registered": {
                    "date": "2017-05-19T08:23:34Z",
                    "age": 1
                },
                "phone": "0022-0499346",
                "cell": "0172-4271690",
                "id": {
                    "name": "",
                    "value": null
                },
                "picture": {
                    "large": "https://randomuser.me/api/portraits/men/56.jpg",
                    "medium": "https://randomuser.me/api/portraits/med/men/56.jpg",
                    "thumbnail": "https://randomuser.me/api/portraits/thumb/men/56.jpg"
                },
                "nat": "DE"
            },
            {
                "gender": "male",
                "name": {
                    "title": "mr",
                    "first": "william",
                    "last": "walker"
                },
                "location": {
                    "street": "4461 bollinger rd",
                    "city": "hervey bay",
                    "state": "victoria",
                    "postcode": 603,
                    "coordinates": {
                        "latitude": "-51.4276",
                        "longitude": "85.3861"
                    },
                    "timezone": {
                        "offset": "+3:30",
                        "description": "Tehran"
                    }
                },
                "email": "william.walker@example.com",
                "login": {
                    "uuid": "05b120d7-7dfa-40f1-aefe-cef099e5b8ac",
                    "username": "greenwolf595",
                    "password": "lesbians",
                    "salt": "2AWryUai",
                    "md5": "99a326a83c9d30a228e505d02ce64d7f",
                    "sha1": "ef7fe5cd8275a511296567265fe1a5cd3dbd8f98",
                    "sha256": "4dd6123a5f39c628a38d2f3a6075aed1f31a80f68cd3632c62a6f2d4b6c8502e"
                },
                "dob": {
                    "date": "1974-09-27T17:39:38Z",
                    "age": 44
                },
                "registered": {
                    "date": "2017-11-30T01:20:32Z",
                    "age": 1
                },
                "phone": "07-4808-7600",
                "cell": "0481-841-242",
                "id": {
                    "name": "TFN",
                    "value": "813607817"
                },
                "picture": {
                    "large": "https://randomuser.me/api/portraits/men/47.jpg",
                    "medium": "https://randomuser.me/api/portraits/med/men/47.jpg",
                    "thumbnail": "https://randomuser.me/api/portraits/thumb/men/47.jpg"
                },
                "nat": "AU"
            }
        ]